{
    "studentList" : [
        {
         "id" : "1",
         "firstName" : "kishore",
         "lastName" : "atla",
         "email" : "abc@gmail.com",
         "phone" : "1234567892",
         "country" : "India",
         "ruralorurban" : "rural",
         "block" : "A-block",
         "village" : "g-palli",
         "city" : "nellore",
         "locality" : "kota",
         "street" : "mittapallem",
         "pincode" : "524411"
        },
        {
         "id" : "2",
         "firstName" : "ramu",
         "lastName" : "batta",
         "email" : "abcefgh@gmail.com",
         "phone" : "1234567892",
         "country" : "India",
         "ruralorurban" : "rural",
         "block" : "d-block",
         "village" : "u-palli",
         "city" : "nellore",
         "locality" : "kota",
         "street" : "chittedu",
         "pincode" : "524481"
        },
        {
         "id" : "3",
         "firstName" : "ani",
         "lastName" : "moddu",
         "email" : "abhjic@gmail.com",
         "phone" : "1234567892",
         "country" : "India",
         "ruralorurban" : "urban",
         "municipality" : "kota",
         "ward" : "genenal",
         "city" : "nellore",
         "locality" : "dagaddrthi",
         "street" : "mittapallem",
         "pincode" : "529411"
        },
        {
         "id" : "4",
         "firstName" : "balu",
         "lastName" : "bolledhu",
         "email" : "bc@gmail.com",
         "phone" : "1234567892",
         "country" : "India",
         "ruralorurban" : "rural",
         "block" : "z-block",
         "village" : "m-palli",
         "city" : "nellore",
         "locality" : "kota",
         "street" : "mittapallem",
         "pincode" : "524411"
        },
        {
         "id" : "5",
         "firstName" : "venu",
         "lastName" : "atla",
         "email" : "vc24@gmail.com",
         "phone" : "1234567892",
         "country" : "India",
         "ruralorurban" : "rural",
         "block" : "x-block",
         "village" : "gdr",
         "city" : "nellore",
         "locality" : "kota",
         "street" : "doravasatram",
         "pincode" : "584411"
        },
 
        {
         "id" : "6",
         "firstName" : "janu",
         "lastName" : "v",
         "email" : "bvh@gmail.com",
         "phone" : "1234567892",
         "country" : "India",
         "ruralorurban" : "urban",
         "block" : "",
         "village" : "mgb",
         "city" : "kavali",
         "locality" : "nellore",
         "street" : "satram",
         "pincode" : "589411"
        },
        {
         "id" : "7",
         "firstName" : "dhana",
         "lastName" : "batta",
         "email" : "bhd@gmail.com",
         "phone" : "1234567892",
         "country" : "India",
         "ruralorurban" : "rural",
         "block" : "x-block",
         "village" : "mgb",
         "city" : "kota",
         "locality" : "dv",
         "street" : "peta",
         "pincode" : "588411"
        }
     ]
 }